[
  {
    "date": "2026-07-01",
    "dayName": "TODAY",
    "fishingScore": 80,
    "scoreLabel": "EXCELLENT",
    "bestWindowStart": "00:00",
    "bestWindowEnd": "03:00",
    "windDir": "NW",
    "windSpeedKmh": 9,
    "precipMm": 0,
    "moonPhase": "waning-gibbous",
    "moonIllumination": 98
  },
  {
    "date": "2026-07-02",
    "dayName": "THU",
    "fishingScore": 76,
    "scoreLabel": "GOOD",
    "bestWindowStart": "20:00",
    "bestWindowEnd": "23:00",
    "windDir": "W",
    "windSpeedKmh": 13,
    "precipMm": 0.3,
    "moonPhase": "waning-gibbous",
    "moonIllumination": 94
  },
  {
    "date": "2026-07-03",
    "dayName": "FRI",
    "fishingScore": 80,
    "scoreLabel": "EXCELLENT",
    "bestWindowStart": "00:00",
    "bestWindowEnd": "03:00",
    "windDir": "W",
    "windSpeedKmh": 7,
    "precipMm": 0,
    "moonPhase": "waning-gibbous",
    "moonIllumination": 89
  },
  {
    "date": "2026-07-04",
    "dayName": "SAT",
    "fishingScore": 77,
    "scoreLabel": "GOOD",
    "bestWindowStart": "01:00",
    "bestWindowEnd": "04:00",
    "windDir": "SW",
    "windSpeedKmh": 13,
    "precipMm": 0,
    "moonPhase": "waning-gibbous",
    "moonIllumination": 82
  },
  {
    "date": "2026-07-05",
    "dayName": "SUN",
    "fishingScore": 76,
    "scoreLabel": "GOOD",
    "bestWindowStart": "04:00",
    "bestWindowEnd": "07:00",
    "windDir": "NW",
    "windSpeedKmh": 11,
    "precipMm": 0.3,
    "moonPhase": "waning-gibbous",
    "moonIllumination": 73
  },
  {
    "date": "2026-07-06",
    "dayName": "MON",
    "fishingScore": 77,
    "scoreLabel": "GOOD",
    "bestWindowStart": "07:00",
    "bestWindowEnd": "10:00",
    "windDir": "NW",
    "windSpeedKmh": 14,
    "precipMm": 0,
    "moonPhase": "waning-gibbous",
    "moonIllumination": 63
  },
  {
    "date": "2026-07-07",
    "dayName": "TUE",
    "fishingScore": 70,
    "scoreLabel": "GOOD",
    "bestWindowStart": "20:00",
    "bestWindowEnd": "23:00",
    "windDir": "NW",
    "windSpeedKmh": 14,
    "precipMm": 1.8,
    "moonPhase": "last-quarter",
    "moonIllumination": 52
  },
  {
    "date": "2026-07-08",
    "dayName": "WED",
    "fishingScore": 80,
    "scoreLabel": "EXCELLENT",
    "bestWindowStart": "00:00",
    "bestWindowEnd": "03:00",
    "windDir": "N",
    "windSpeedKmh": 7,
    "precipMm": 0,
    "moonPhase": "waning-crescent",
    "moonIllumination": 41
  },
  {
    "date": "2026-07-09",
    "dayName": "THU",
    "fishingScore": 80,
    "scoreLabel": "EXCELLENT",
    "bestWindowStart": "00:00",
    "bestWindowEnd": "03:00",
    "windDir": "SW",
    "windSpeedKmh": 4,
    "precipMm": 0,
    "moonPhase": "waning-crescent",
    "moonIllumination": 30
  },
  {
    "date": "2026-07-10",
    "dayName": "FRI",
    "fishingScore": 74,
    "scoreLabel": "GOOD",
    "bestWindowStart": "00:00",
    "bestWindowEnd": "03:00",
    "windDir": "SW",
    "windSpeedKmh": 7,
    "precipMm": 0,
    "moonPhase": "waning-crescent",
    "moonIllumination": 20
  },
  {
    "date": "2026-07-11",
    "dayName": "SAT",
    "fishingScore": 74,
    "scoreLabel": "GOOD",
    "bestWindowStart": "19:00",
    "bestWindowEnd": "22:00",
    "windDir": "NW",
    "windSpeedKmh": 9,
    "precipMm": 0,
    "moonPhase": "waning-crescent",
    "moonIllumination": 11
  },
  {
    "date": "2026-07-12",
    "dayName": "SUN",
    "fishingScore": 77,
    "scoreLabel": "GOOD",
    "bestWindowStart": "20:00",
    "bestWindowEnd": "23:00",
    "windDir": "N",
    "windSpeedKmh": 12,
    "precipMm": 0,
    "moonPhase": "waning-crescent",
    "moonIllumination": 5
  },
  {
    "date": "2026-07-13",
    "dayName": "MON",
    "fishingScore": 78,
    "scoreLabel": "GOOD",
    "bestWindowStart": "00:00",
    "bestWindowEnd": "03:00",
    "windDir": "W",
    "windSpeedKmh": 7,
    "precipMm": 0.3,
    "moonPhase": "waning-crescent",
    "moonIllumination": 1
  },
  {
    "date": "2026-07-14",
    "dayName": "TUE",
    "fishingScore": 76,
    "scoreLabel": "GOOD",
    "bestWindowStart": "00:00",
    "bestWindowEnd": "03:00",
    "windDir": "NW",
    "windSpeedKmh": 12,
    "precipMm": 0.9,
    "moonPhase": "new",
    "moonIllumination": 0
  }
]
